{"frameRate":24,"name":"coin","version":"5.5","compatibleVersion":"5.5","armature":[{"type":"Sheet","frameRate":24,"name":"Sprite","aabb":{"x":-390,"y":-390,"width":780,"height":780},"bone":[{"name":"root"}],"slot":[{"displayIndex":1,"name":"sheetSlot","parent":"root"}],"skin":[{"slot":[{"name":"sheetSlot","display":[{"name":"Coin_1"},{"name":"Coin_15"},{"name":"Coin_14"},{"name":"Coin_13"},{"name":"Coin_12"},{"name":"Coin_11"},{"name":"Coin_10"},{"name":"Coin_9"},{"name":"Coin_8"},{"name":"Coin_7"},{"name":"Coin_6"},{"name":"Coin_5"},{"name":"Coin_4"},{"name":"Coin_3"},{"name":"Coin_2"}]}]}],"animation":[{"duration":15,"playTimes":0,"name":"Sprite","slot":[{"name":"sheetSlot","displayFrame":[{},{"value":1},{"value":2},{"value":3},{"value":4},{"value":5},{"value":6},{"value":7},{"value":8},{"value":9},{"value":10},{"value":11},{"value":12},{"value":13},{"value":14}]}]}],"defaultActions":[{"gotoAndPlay":"Sprite"}]}]}